odoo/addons/mail_activity_dashboard/README.rst
odoo/addons/mail_activity_dashboard/__init__.py
odoo/addons/mail_activity_dashboard/__manifest__.py
odoo/addons/mail_activity_dashboard/i18n/it.po
odoo/addons/mail_activity_dashboard/i18n/mail_activity_dashboard.pot
odoo/addons/mail_activity_dashboard/readme/CONTRIBUTORS.md
odoo/addons/mail_activity_dashboard/readme/DESCRIPTION.md
odoo/addons/mail_activity_dashboard/security/groups.xml
odoo/addons/mail_activity_dashboard/static/description/icon.png
odoo/addons/mail_activity_dashboard/static/description/index.html
odoo/addons/mail_activity_dashboard/views/mail_activity_view.xml
odoo_addon_mail_activity_dashboard-18.0.1.0.0.4.dist-info/METADATA
odoo_addon_mail_activity_dashboard-18.0.1.0.0.4.dist-info/WHEEL
odoo_addon_mail_activity_dashboard-18.0.1.0.0.4.dist-info/top_level.txt
odoo_addon_mail_activity_dashboard-18.0.1.0.0.4.dist-info/RECORD
