Metadata-Version: 2.1
Name: odoo-addon-mail_activity_dashboard
Version: 18.0.1.0.0.4
Requires-Python: >=3.10
Requires-Dist: odoo-addon-mail_activity_board==18.0.*
Requires-Dist: odoo==18.0.*
Summary: Add Activity Dashboards
Home-page: https://github.com/OCA/mail
License: AGPL-3
Author: SDi, David Juaneda, Sodexis, ACSONE SA/NV, Odoo Community Association (OCA)
Author-email: support@odoo-community.org
Classifier: Programming Language :: Python
Classifier: Framework :: Odoo
Classifier: Framework :: Odoo :: 18.0
Classifier: License :: OSI Approved :: GNU Affero General Public License v3
Classifier: Development Status :: 4 - Beta
